{
  "project_info": {
    "project_number": "123456789012",
    "project_id": "carpolly-dummy",
    "storage_bucket": "carpolly-dummy.appspot.com"
  },
  "client": [
    {
      "client_info": {
        "mobilesdk_app_id": "1:123456789012:android:abcdef1234567890abcdef",
        "android_client_info": {
          "package_name": "com.carpolly.reactnative"
        }
      },
      "oauth_client": [],
      "api_key": [
        {
          "current_key": "dummy_api_key_for_local_dev"
        }
      ],
      "services": {
        "appinvite_service": {
          "other_platform_oauth_client": []
        }
      }
    }
  ],
  "configuration_version": "1"
}